{
  "generator-jhipster": {
    "promptValues": {
      "packageName": "in.etbot",
      "nativeLanguage": "en"
    },
    "jhipsterVersion": "6.10.5",
    "applicationType": "monolith",
    "baseName": "8bot",
    "packageName": "in.etbot",
    "packageFolder": "in/etbot",
    "serverPort": "8080",
    "authenticationType": "jwt",
    "cacheProvider": "ehcache",
    "enableHibernateCache": false,
    "websocket": false,
    "databaseType": "mongodb",
    "devDatabaseType": "mongodb",
    "prodDatabaseType": "mongodb",
    "searchEngine": false,
    "messageBroker": false,
    "serviceDiscoveryType": "eureka",
    "buildTool": "maven",
    "enableSwaggerCodegen": false,
    "jwtSecretKey": "ZGQ2NGFlZDdmOGU0NWM1YTNmNmQ2MDEzZDczYWI1YjJiYWVmZTgyOGU4YzM3NzkyMzY5YjRjYWNlNzQ1MDIyMjI1YjQxODlkZDIxYzM4ZjgxMGU5ZWJlZmMyYWE2ZjliNWMwZWI0YjM5ZjE3YjcxZTQ4NGRlNTYwZTRkZGQ1MzI=",
    "embeddableLaunchScript": false,
    "useSass": true,
    "clientPackageManager": "npm",
    "clientFramework": "react",
    "clientTheme": "darkly",
    "clientThemeVariant": "dark",
    "creationTimestamp": 1608501287653,
    "testFrameworks": [],
    "jhiPrefix": "jhi",
    "entitySuffix": "",
    "dtoSuffix": "DTO",
    "otherModules": [],
    "enableTranslation": true,
    "nativeLanguage": "en",
    "languages": ["en"],
    "blueprints": []
  }
}
